pyrequirements/__init__.py
pyrequirements/_version.py
pyrequirements/conf.py
pyrequirements/core.py
pyrequirements/list.py
pyrequirements/main.py
pyrequirements/resource/requirements.ini
PyRequirements-0.1.3.dist-info/DESCRIPTION.rst
PyRequirements-0.1.3.dist-info/entry_points.txt
PyRequirements-0.1.3.dist-info/METADATA
PyRequirements-0.1.3.dist-info/metadata.json
PyRequirements-0.1.3.dist-info/RECORD
PyRequirements-0.1.3.dist-info/top_level.txt
PyRequirements-0.1.3.dist-info/WHEEL
