Metadata-Version: 2.0
Name: PyRequirements
Version: 0.1.3
Summary: python requirements dynamic generation
Home-page: https://github.com/x007007007/pyrequirements/
Author: xuxingci
Author-email: x007007007@hotmail.com
License: MIT
Platform: RaspberryPi
Platform: Linux
Platform: Unix
Platform: Window
Platform: MacOS
Classifier: Intended Audience :: Developers
Classifier: Operating System :: POSIX :: Linux
Classifier: Operating System :: POSIX
Classifier: Operating System :: MacOS
Classifier: Operating System :: Microsoft
Classifier: Programming Language :: Python
Requires-Dist: pip
